richify/__init__.py
richify/richify.py
richify-0.0.2.dist-info/LICENSE
richify-0.0.2.dist-info/METADATA
richify-0.0.2.dist-info/WHEEL
richify-0.0.2.dist-info/entry_points.txt
richify-0.0.2.dist-info/top_level.txt
richify-0.0.2.dist-info/RECORD
