Metadata-Version: 2.1
Name: richify
Version: 0.0.2
Summary: Rich highlight arbitrary text output in your terminal
Home-page: https://github.com/coryg89/richify
Author: Cory Gross
Author-email: coryg89@gmail.com
Project-URL: Bug Tracker, https://github.com/coryg89/richify/issues
Classifier: Programming Language :: Python :: 3
Classifier: License :: OSI Approved :: MIT License
Classifier: Operating System :: OS Independent
Requires-Python: >=3.6
License-File: LICENSE
